dudwalls.py
dudwalls_python-1.0.0.dist-info/METADATA
dudwalls_python-1.0.0.dist-info/WHEEL
dudwalls_python-1.0.0.dist-info/top_level.txt
dudwalls_python-1.0.0.dist-info/RECORD
